odoo8_addon_operating_unit-8.0.1.0.0.99.dev6-py2.7-nspkg.pth
odoo_addons/operating_unit/__openerp__.py
odoo_addons/operating_unit/__init__.py
odoo_addons/operating_unit/README.rst
odoo_addons/operating_unit/security/operating_unit_security.xml
odoo_addons/operating_unit/security/ir.model.access.csv
odoo_addons/operating_unit/view/operating_unit_view.xml
odoo_addons/operating_unit/view/res_users_view.xml
odoo_addons/operating_unit/models/operating_unit.py
odoo_addons/operating_unit/models/__init__.py
odoo_addons/operating_unit/models/res_users.py
odoo_addons/operating_unit/data/operating_unit_data.xml
odoo_addons/operating_unit/demo/operating_unit_demo.xml
odoo_addons/operating_unit/static/description/icon.png
odoo8_addon_operating_unit-8.0.1.0.0.99.dev6.dist-info/top_level.txt
odoo8_addon_operating_unit-8.0.1.0.0.99.dev6.dist-info/WHEEL
odoo8_addon_operating_unit-8.0.1.0.0.99.dev6.dist-info/RECORD
odoo8_addon_operating_unit-8.0.1.0.0.99.dev6.dist-info/metadata.json
odoo8_addon_operating_unit-8.0.1.0.0.99.dev6.dist-info/DESCRIPTION.rst
odoo8_addon_operating_unit-8.0.1.0.0.99.dev6.dist-info/METADATA
odoo8_addon_operating_unit-8.0.1.0.0.99.dev6.dist-info/namespace_packages.txt
