Metadata-Version: 2.0
Name: odoo8-addon-operating-unit
Version: 8.0.1.0.0.99.dev6
Summary: An operating unit (OU) is an organizational entity part of a company
Home-page: http://www.eficent.com
Author: Eficent Business and IT Consulting Services S.L., Serpent Consulting Services Pvt. Ltd.,Odoo Community Association (OCA)
Author-email: support@odoo-community.org
License: AGPL-3
Platform: UNKNOWN
Requires-Dist: odoo (<9.0a,>=8.0a)
Classifier: Programming Language :: Python :: 2.7
Classifier: Framework :: Odoo
Classifier: License :: OSI Approved :: GNU Affero General Public License v3
